{"result_summary":"카카오 최신 뉴스 3건 수집을 위한 검색 기준 설계 완료. 검색 키워드 6개(한국어 5개+영문 1개), 신뢰 출처 Tier 3단계(Tier1: 연합뉴스·한국경제·매일경제·조선일보 등 4개사, Tier2: 서울경제·머니투데이·이데일리·ZDNet Korea 등 4개사), 결과 포맷(제목·2~3문장 요약·링크·날짜·출처 5개 필드) 확정. 파일 저장은 권한 문제로 미완료.","deliverables":["검색 키워드 리스트 6개 정의 (한국어 5개 + 영문 1개, 우선순위 순)","신뢰 출처 Tier 기준: Tier1(4개사)·Tier2(4개사)·Tier3(블로그형 참고용) 및 제외 기준","결과 포맷 명세: 제목/요약(2~3문장·누가-무엇-왜)/링크/날짜(YYYY-MM-DD)/출처 5개 필드","워커 실행 체크리스트 6단계","품질 기준 5개 항목(최신성·신뢰도·요약품질·링크유효성·중복금지)"],"issues_encountered":["data/outputs 디렉토리 파일 쓰기 권한 거부로 설계서 파일 생성 미완료 — 결과는 StructuredOutput으로 대체 보고"],"completion_percentage":85,"deliverable_files":[],"is_partial":false,"labeled_findings":[{"content":"검색 키워드 6개: ①카카오 ②카카오 뉴스 2026 ③카카오 최근 소식 ④Kakao ⑤카카오 공시 ⑥카카오톡 카카오페이 카카오모빌리티 — 1번부터 순차 시도, 3건 미달 시 보완 키워드 사용","category":"recommendation","importance":5,"source":""},{"content":"신뢰 출처 Tier1(최우선): 연합뉴스(국가 공식 통신사), 한국경제(IT·기업 전문), 매일경제(경영·실적 전문), 조선일보(검증 체계). 이 4개사 기사 우선 선별","category":"fact","importance":5,"source":""},{"content":"결과 포맷 5개 필드 확정: 제목(전문), 요약(2~3문장·누가/무엇을/왜 구조), 링크(원문 직접 URL), 날짜(YYYY-MM-DD), 출처(언론사명)","category":"fact","importance":5,"source":""},{"content":"신뢰 출처 Tier2(권장): 서울경제, 머니투데이, 이데일리, ZDNet Korea — Tier1 기사 부족 시 보완","category":"fact","importance":4,"source":""},{"content":"제외 기준: 광고성 PR 기사, 출처 불명 자료, 포털 요약본(원문 링크 없는 경우). 포털 캐시 URL도 불허","category":"recommendation","importance":4,"source":""},{"content":"품질 기준: 최신성(7일 이내), 신뢰도(Tier1~2), 요약품질(2~3문장), 링크유효성(원문 직접), 중복금지(동일기사 불허)","category":"analysis","importance":3,"source":""},{"content":"워커 실행 순서: 키워드1 검색 → Tier1 선별 → 최신 3건 날짜 내림차순 선택 → 링크 유효성 확인 → 포맷 기재 → 3건 미달 시 보완 키워드","category":"recommendation","importance":3,"source":""}],"reflection_passed":true,"reflection_repaired":false}